{
    "name": "pyramide-sender-bot",
    "version": "1.0.0",
    "description": "Telegram bot for Pyramide Sender with Plesk integration",
    "main": "index.mjs",
    "type": "module",
    "scripts": {
      "start": "node index.mjs",
      "dev": "nodemon index.mjs"
    },
    "dependencies": {
      "telegraf": "^4.12.2",
      "mongoose": "^7.3.1",
      "moment-timezone": "^0.5.43",
      "node-fetch": "^3.3.1",
      "nanoid": "^4.0.2",
      "axios": "^0.21.1",
      "express": "^4.17.1",
      "generate-password": "^1.7.0"
    },
    "devDependencies": {
      "nodemon": "^2.0.22"
    },
    "engines": {
      "node": ">=14.0.0"
    },
    "author": "",
    "license": "ISC"
  }